s3duct/__init__.py
s3duct/backpressure.py
s3duct/chunker.py
s3duct/cli.py
s3duct/config.py
s3duct/downloader.py
s3duct/encryption.py
s3duct/integrity.py
s3duct/manifest.py
s3duct/py.typed
s3duct/resume.py
s3duct/thaw.py
s3duct/uploader.py
s3duct/backends/__init__.py
s3duct/backends/base.py
s3duct/backends/local.py
s3duct/backends/s3.py
s3duct-0.3.1.dist-info/licenses/LICENSE
s3duct-0.3.1.dist-info/METADATA
s3duct-0.3.1.dist-info/WHEEL
s3duct-0.3.1.dist-info/entry_points.txt
s3duct-0.3.1.dist-info/top_level.txt
s3duct-0.3.1.dist-info/RECORD
