Metadata-Version: 2.4
Name: s3duct
Version: 0.3.1
Summary: Chunked, resumable, encrypted pipe to S3-compatible object storage
Author: Site Reliability Enby
License-Expression: Elastic-2.0
Project-URL: Repository, https://github.com/SiteRelEnby/s3duct
Project-URL: Issues, https://github.com/SiteRelEnby/s3duct/issues
Keywords: s3,backup,streaming,encryption,chunked,resumable,object-storage,pipe,aes-gcm,age
Classifier: Development Status :: 3 - Alpha
Classifier: Environment :: Console
Classifier: Intended Audience :: System Administrators
Classifier: Intended Audience :: Developers
Classifier: Operating System :: POSIX
Classifier: Operating System :: MacOS
Classifier: Programming Language :: Python :: 3
Classifier: Programming Language :: Python :: 3.10
Classifier: Programming Language :: Python :: 3.11
Classifier: Programming Language :: Python :: 3.12
Classifier: Topic :: System :: Archiving :: Backup
Classifier: Topic :: System :: Systems Administration
Classifier: Typing :: Typed
Requires-Python: >=3.10
License-File: LICENSE
Requires-Dist: boto3>=1.28
Requires-Dist: click>=8.0
Requires-Dist: cryptography>=41.0
Provides-Extra: dev
Requires-Dist: pytest>=7.0; extra == "dev"
Requires-Dist: moto[s3]>=4.0; extra == "dev"
Requires-Dist: pytest-asyncio>=0.21; extra == "dev"
Dynamic: license-file
